{
  "history": [
    {
      "wallet": "5A5YzhqDqKzWqY3nDawyubUDNVYZbsCN6HS4tqih5FCJ",
      "amount": 0.02975343,
      "timestamp": 1746182437,
      "countdownEnd": 1746186037
    },
    {
      "wallet": "CXiR4yiadJRG26h7ahhrXESZNZKscug7yeej8h1wfJYA",
      "amount": 0.000251974,
      "timestamp": 1746178356,
      "countdownEnd": 1746181956
    },
    {
      "wallet": "Hm6RD49cJ4hYVa7iLcoAuXDJ9cSGbihbS8Hheg2GxSdh",
      "amount": 0.002814508,
      "timestamp": 1746174695,
      "countdownEnd": 1746178295
    },
    {
      "wallet": "8ZHPNFuBSF4roX82uWXyRczudo5SkA7MgEjQDHSkE7qN",
      "amount": 0.028828019,
      "timestamp": 1746171038,
      "countdownEnd": 1746174638
    },
    {
      "wallet": "7bZ4ZkUeKB74He9F5BNDarW8UfMnzAqbEmT8x1ksjQ3P",
      "amount": 0.000271458,
      "timestamp": 1746162756,
      "countdownEnd": 1746166356
    }
  ],
  "current": {
    "wallet": "5A5YzhqDqKzWqY3nDawyubUDNVYZbsCN6HS4tqih5FCJ",
    "amount": 0.02975343,
    "timestamp": 1746182437,
    "countdownEnd": 1746186037
  }
}